clyro/__init__.py
clyro/py.typed
clyro-0.1.0.dist-info/WHEEL
clyro-0.1.0.dist-info/METADATA
clyro-0.1.0.dist-info/RECORD
