Metadata-Version: 2.3
Name: clyro
Version: 0.1.0
Summary: Clyro - The intelligent core for AI agents
Keywords: clyro,agents,ai
Author: Sumanth
Author-email: Sumanth <hello@clyro.dev>
Classifier: Development Status :: 2 - Pre-Alpha
Classifier: Intended Audience :: Developers
Classifier: License :: OSI Approved :: MIT License
Classifier: Programming Language :: Python :: 3
Classifier: Programming Language :: Python :: 3.9
Classifier: Programming Language :: Python :: 3.10
Classifier: Programming Language :: Python :: 3.11
Classifier: Programming Language :: Python :: 3.12
Requires-Python: >=3.11
